falconpy/__init__.py
falconpy/_hal.py
falconpy2-2.0.1.dist-info/licenses/LICENSE
falconpy2-2.0.1.dist-info/METADATA
falconpy2-2.0.1.dist-info/WHEEL
falconpy2-2.0.1.dist-info/top_level.txt
falconpy2-2.0.1.dist-info/RECORD
