Metadata-Version: 2.4
Name: falconpy2
Version: 2.0.1
Summary: FalconPy2”
Author: NetrisCS
License: Unlicense
Project-URL: Homepage, https://www.netriscs.com/
Classifier: Programming Language :: Python :: 3
Classifier: License :: Public Domain
Requires-Python: >=3.8
License-File: LICENSE
Dynamic: license-file
